modelservice/__init__.py
modelservice/admin.py
modelservice/apps.py
modelservice/base.py
modelservice/callees.py
modelservice/conf.py
modelservice/profiler.py
modelservice/pubsub.py
modelservice/urls.py
modelservice/webhooks.py
modelservice/crossbar/__init__.py
modelservice/crossbar/guest/__init__.py
modelservice/crossbar/profiler/__init__.py
modelservice/crossbar/profiler/discovery.py
modelservice/crossbar/profiler/worker.py
modelservice/crossbar/runner/__init__.py
modelservice/games/__init__.py
modelservice/games/decorators.py
modelservice/games/inspector.py
modelservice/games/registry.py
modelservice/games/storages.py
modelservice/games/scopes/__init__.py
modelservice/games/scopes/base.py
modelservice/games/scopes/concrete.py
modelservice/games/scopes/constants.py
modelservice/games/scopes/exceptions.py
modelservice/games/scopes/managers.py
modelservice/games/scopes/traversing.py
modelservice/games/scopes/wamp.py
modelservice/games/scopes/webhooks.py
modelservice/management/__init__.py
modelservice/management/commands/__init__.py
modelservice/management/commands/aws_profiler.py
modelservice/management/commands/profile.py
modelservice/management/commands/run_guest.py
modelservice/management/commands/run_modelservice.py
modelservice/migrations/__init__.py
modelservice/profiles/__init__.py
modelservice/profiles/profile_http.py
modelservice/profiles/profile_pubsub.py
modelservice/simpl/__init__.py
modelservice/simpl/asyn.py
modelservice/simpl/syn.py
modelservice/static/modelservice/monitor/index.html
modelservice/static/modelservice/monitor/js/autobahn.min.js
modelservice/templates/modelservice/config.json.tpl
modelservice/utils/__init__.py
modelservice/utils/asyncio.py
modelservice/utils/aws_profiler_management.py
modelservice/utils/functional.py
modelservice/utils/instruments.py
modelservice/utils/scopes.py
modelservice/utils/strings.py
simpl_modelservice-0.10.1.data/scripts/aws_profile.sh
simpl_modelservice-0.10.1.data/scripts/profile.sh
simpl_modelservice-0.10.1.dist-info/LICENSE
simpl_modelservice-0.10.1.dist-info/METADATA
simpl_modelservice-0.10.1.dist-info/WHEEL
simpl_modelservice-0.10.1.dist-info/dependency_links.txt
simpl_modelservice-0.10.1.dist-info/top_level.txt
simpl_modelservice-0.10.1.dist-info/RECORD
