Metadata-Version: 2.1
Name: simpl-modelservice
Version: 0.10.1
Summary: Python Library to implement Simulations, built on Crossbar.io and Django.
Home-page: https://github.com/simplworld/simpl-modelservice
Author: 
Author-email: 
License: UNKNOWN
Platform: UNKNOWN
Classifier: Development Status :: 4 - Beta
Classifier: Environment :: Web Environment
Classifier: Intended Audience :: Developers
Classifier: License :: OSI Approved :: GNU General Public License v2 (GPLv2)
Classifier: Operating System :: OS Independent
Classifier: Programming Language :: Python :: 3
Classifier: Framework :: Django
License-File: LICENSE
Requires-Dist: simpl-authenticator (==0.7.3)
Requires-Dist: simpl-client (~=0.8.0)
Requires-Dist: django (~=2.2.0)
Requires-Dist: djangorestframework (~=3.9.0)
Requires-Dist: aiorwlock
Requires-Dist: aiojobs (==0.2.1)
Requires-Dist: attrs (>=17.4.0)
Requires-Dist: autobahn (==17.10.1)
Requires-Dist: click (==6.7)
Requires-Dist: crossbar (==17.10.1)
Requires-Dist: django-markup (==1.2)
Requires-Dist: django-click (==2.1.0)
Requires-Dist: thorn
Requires-Dist: twisted (==20.3.0)
